{"cameraMode":{"drawMode":0,"name":"Shaded","section":"Shading Mode"},"sceneLighting":false,"audioPlay":false,"sceneViewState":{"showFog":true,"showMaterialUpdate":false,"showSkybox":false,"showFlares":true,"showImageEffects":true,"showParticleSystems":true},"in2DMode":false,"pivot":{"x":-3.1688761711120607,"y":2.1001365184783937,"z":1.2176772356033326},"rotation":{"x":0.0033347904682159425,"y":0.967757523059845,"z":0.012762919068336487,"w":-0.2516341507434845},"size":2.8300893306732179,"orthographic":false}